LICENSE
MANIFEST.in
README.rst
erequests.py
setup.py
erequests.egg-info/PKG-INFO
erequests.egg-info/SOURCES.txt
erequests.egg-info/dependency_links.txt
erequests.egg-info/not-zip-safe
erequests.egg-info/requires.txt
erequests.egg-info/top_level.txt
tests/__init__.py
tests/test_erequests.py