Metadata-Version: 1.1
Name: erequests
Version: 0.3.0
Summary: Requests + Eventlet
Home-page: https://github.com/saghul/erequests
Author: Saúl Ibarra Corretgé
Author-email: saghul@gmail.com
License: BSD
Platform: any
Classifier: Environment :: Web Environment
Classifier: Intended Audience :: Developers
Classifier: License :: OSI Approved :: BSD License
Classifier: Operating System :: OS Independent
Classifier: Programming Language :: Python
Classifier: Topic :: Internet :: WWW/HTTP :: Dynamic Content
Classifier: Topic :: Software Development :: Libraries :: Python Modules
